compas_shapeop/meshsolver.py
compas_shapeop/_shapeop.cpython-39-darwin.so
compas_shapeop/__init__.py
compas_shapeop/shapeop.py
compas_shapeop/__main__.py
compas_shapeop-0.1.2.dist-info/RECORD
compas_shapeop-0.1.2.dist-info/WHEEL
compas_shapeop-0.1.2.dist-info/METADATA
compas_shapeop-0.1.2.dist-info/licenses/AUTHORS.md
compas_shapeop-0.1.2.dist-info/licenses/LICENSE
compas_shapeop-0.1.2.dist-info/licenses/LICENSE.shapeop
