Metadata-Version: 2.1
Name: compas_shapeop
Version: 0.1.2
Summary: ShapeOp wrapper for COMPAS.
Author-Email: Petras Vestartas <petrasvestartas@gmail.com>, Tom Van Mele <tom.v.mele@gmail.com>
Classifier: Development Status :: 4 - Beta
Classifier: Topic :: Scientific/Engineering
Classifier: Operating System :: Unix
Classifier: Operating System :: POSIX
Classifier: Operating System :: Microsoft :: Windows
Classifier: Programming Language :: Python
Classifier: Programming Language :: Python :: 3
Classifier: Programming Language :: Python :: 3.9
Classifier: Programming Language :: Python :: 3.10
Classifier: Programming Language :: Python :: 3.11
Classifier: Programming Language :: Python :: 3.12
Classifier: License :: OSI Approved :: BSD License
Project-URL: Homepage, https://blockresearchgroup.github.io/compas_shapeop
Project-URL: Documentation, https://blockresearchgroup.github.io/compas_shapeop
Project-URL: Repository, https://github.com/blockresearchgroup/compas_shapeop
Project-URL: Changelog, https://github.com/blockresearchgroup/compas_shapeop/blob/main/CHANGELOG.md
Project-URL: Issues, https://github.com/blockresearchgroup/compas_shapeop/issues
Project-URL: Forum, https://forum.compas-framework.org/
Requires-Python: >=3.9
